m3loader/__init__.py
m3loader/dloader.py
m3loader-0.2.5.dist-info/LICENSE
m3loader-0.2.5.dist-info/METADATA
m3loader-0.2.5.dist-info/WHEEL
m3loader-0.2.5.dist-info/entry_points.txt
m3loader-0.2.5.dist-info/top_level.txt
m3loader-0.2.5.dist-info/RECORD
