Metadata-Version: 2.1
Name: m3loader
Version: 0.2.5
Summary: A tool to download and merge M3U8 segments into an MP4 file.
Home-page: https://github.com/d4r5hE/m3loader
Author: Darsh
Author-email: darsh.564742@gmail.com
License: MIT
Classifier: Development Status :: 3 - Alpha
Classifier: Intended Audience :: Developers
Classifier: License :: OSI Approved :: MIT License
Classifier: Programming Language :: Python :: 3
Classifier: Programming Language :: Python :: 3.8
Classifier: Programming Language :: Python :: 3.9
Classifier: Programming Language :: Python :: 3.10
Requires-Python: >=3.6
License-File: LICENSE
Requires-Dist: aiohttp
Requires-Dist: tqdm
Requires-Dist: ffmpeg-python
